auledft/__init__.py
auledft/cli.py
auledft-0.1.0.dist-info/LICENSE
auledft-0.1.0.dist-info/METADATA
auledft-0.1.0.dist-info/WHEEL
auledft-0.1.0.dist-info/entry_points.txt
auledft-0.1.0.dist-info/top_level.txt
auledft-0.1.0.dist-info/RECORD
