Metadata-Version: 2.2
Name: auledft
Version: 0.1.0
License-File: LICENSE
Requires-Dist: ase
Requires-Dist: numpy
Requires-Dist: click
Requires-Dist: streamlit
Dynamic: requires-dist
